rosdistro/__init__.py
rosdistro/aptdistro.py
rosdistro/common.py
rosdistro/dependency_walker.py
rosdistro/develdistro.py
rosdistro/distribution.py
rosdistro/distribution_cache.py
rosdistro/distribution_cache_generator.py
rosdistro/distribution_file.py
rosdistro/doc_build_file.py
rosdistro/doc_file.py
rosdistro/doc_repository_specification.py
rosdistro/freeze_source.py
rosdistro/index.py
rosdistro/legacy.py
rosdistro/loader.py
rosdistro/package.py
rosdistro/release.py
rosdistro/release_build.py
rosdistro/release_build_file.py
rosdistro/release_cache.py
rosdistro/release_cache_generator.py
rosdistro/release_file.py
rosdistro/release_repository_specification.py
rosdistro/repository.py
rosdistro/repository_specification.py
rosdistro/rosdistro.py
rosdistro/source_build_file.py
rosdistro/source_file.py
rosdistro/source_repository_cache.py
rosdistro/source_repository_specification.py
rosdistro/status.py
rosdistro/vcs.py
rosdistro/verify.py
rosdistro/writer.py
rosdistro/cli/__init__.py
rosdistro/cli/rosdistro.py
rosdistro/cli/rosdistro_build_cache.py
rosdistro/cli/rosdistro_convert.py
rosdistro/cli/rosdistro_freeze_source.py
rosdistro/cli/rosdistro_generate_cache.py
rosdistro/cli/rosdistro_migrate_to_rep_141.py
rosdistro/cli/rosdistro_migrate_to_rep_143.py
rosdistro/cli/rosdistro_reformat.py
rosdistro/external/__init__.py
rosdistro/external/appdirs.py
rosdistro/manifest_provider/__init__.py
rosdistro/manifest_provider/bitbucket.py
rosdistro/manifest_provider/cache.py
rosdistro/manifest_provider/git.py
rosdistro/manifest_provider/github.py
rosdistro/manifest_provider/tar.py
rosdistro-1.0.1.dist-info/LICENSE.txt
rosdistro-1.0.1.dist-info/METADATA
rosdistro-1.0.1.dist-info/WHEEL
rosdistro-1.0.1.dist-info/entry_points.txt
rosdistro-1.0.1.dist-info/top_level.txt
rosdistro-1.0.1.dist-info/RECORD
